pydantic_validation_formatter/__init__.py
pydantic_validation_formatter-0.1.2.dist-info/LICENSE
pydantic_validation_formatter-0.1.2.dist-info/METADATA
pydantic_validation_formatter-0.1.2.dist-info/WHEEL
pydantic_validation_formatter-0.1.2.dist-info/RECORD
