Metadata-Version: 2.1
Name: pydantic-validation-formatter
Version: 0.1.2
Summary: This is a package that allows to customize pydantic built-in validation error messages
Home-page: https://github.com/soamicharan/pydantic-validation-formatter
License: Apache-2.0
Keywords: python,pydantic,sqlmodel
Author: Soami Charan
Author-email: charansoami@gmail.com
Maintainer: Soami Charan
Maintainer-email: charansoami@gmail.com
Requires-Python: >=3.8,<4.0
Classifier: License :: OSI Approved :: Apache Software License
Classifier: Programming Language :: Python :: 3
Classifier: Programming Language :: Python :: 3.8
Classifier: Programming Language :: Python :: 3.9
Classifier: Programming Language :: Python :: 3.10
Classifier: Programming Language :: Python :: 3.11
Classifier: Programming Language :: Python :: 3.12
Requires-Dist: pydantic (>=2.6.3,<3.0.0)
Project-URL: Repository, https://github.com/soamicharan/pydantic-validation-formatter
